{
    "$schema": "https://raw.githubusercontent.com/DotNetAnalyzers/StyleCopAnalyzers/master/StyleCop.Analyzers/StyleCop.Analyzers/Settings/stylecop.schema.json",
    "settings": {
        "documentationRules": {
            "companyName": "ShoppingProject",
            "copyrightText": "Copyright (c) ShoppingProject. All rights reserved.",
            "documentExposedElements": false,
            "documentInternalElements": false,
            "documentPrivateElements": false,
            "documentInterfaces": false
        },
        "orderingRules": {
            "usingDirectivesPlacement": "outsideNamespace",
            "systemUsingDirectivesFirst": false
        },
        "layoutRules": {
            "newlineAtEndOfFile": "allow"
        },
        "readabilityRules": {
            "allowBuiltInTypeAliases": true
        }
    }
}